simfection/__init__.py
simfection/anchor.py
simfection/arguments.py
simfection/connection_engine.py
simfection/interaction_engine.py
simfection/logger.py
simfection/path.py
simfection/population_engine.py
simfection/settings.py
simfection/simulation_day.py
simfection/simulation_run.py
simfection/update_engine.py
simfection-0.2.0.dist-info/LICENSE
simfection-0.2.0.dist-info/METADATA
simfection-0.2.0.dist-info/WHEEL
simfection-0.2.0.dist-info/entry_points.txt
simfection-0.2.0.dist-info/top_level.txt
simfection-0.2.0.dist-info/RECORD
