Metadata-Version: 2.1
Name: simfection
Version: 0.2.0
Summary: A stochastic, interaction-based infectious disease model
Home-page: https://github.com/simfection/simfection
Author: Simfection Research Group
Author-email: simfectiongroup@gmail.com
License: UNKNOWN
Platform: UNKNOWN
Classifier: Programming Language :: Python :: 3
Classifier: License :: OSI Approved :: MIT License
Requires-Python: >=3.7
Requires-Dist: pandas (==1.0.4)
Requires-Dist: PyYAML (>=5.0.0)
